{"locations":[{"id":0,"name":"SRO Building","address":"109 West 129th Street, Basement, (@ Lenox Avenue) NY 10027","meeting_name":"A CHANCE TO LIVE AGAIN - A Chance To Live Again","meeting_details":""},{"id":1,"name":"Union Baptist Church","address":"240 West 145th Street, (Betw 7th &amp; 8th Avenues) NY 10039","meeting_name":"AA IT WORKS  II - AA It Works II","meeting_details":"Thu=Altern.BB, Living Sober & Other A.A. Literature. Fri.=Alternates between Step & Tradition."},{"id":2,"name":"Our Lady of Lourdes Church","address":"469 West 142nd Street, Basement, (Betw Convent &amp; Amsterdam Avenues) NY 10031","meeting_name":"ATTITUDE ADJUSTMENT - Attitude Adjustment","meeting_details":"Topic 1st Saturday."},{"id":3,"name":"St. Phillip Church","address":"204 West 134th Street, 1st Floor, (Betw 7th &amp; 8th Avenues) 10030","meeting_name":"CONVENT - ","meeting_details":"B-3rd Saturday"},{"id":4,"name":"Spiritual Renewal Church","address":"2044 Adam Clayton Powell Blvd., (@ 122nd Street) NY 10027","meeting_name":"FELLOWSHIP AT NOON - Fellowship At Noon","meeting_details":"T If there is a fifth Wednesday."},{"id":5,"name":"","address":"469 West 142nd Street, 1st Floor, (Betw. Amsterdam &amp; Convent Avenues) 10031","meeting_name":"GRUPO TRASMITELO - ","meeting_details":"Spanish speaking meeting."},{"id":6,"name":"St. Mary's Episcopal","address":"521 W 126th St, Amsterdam &amp; Old Broadway 10027","meeting_name":"HARLEM HUMANISTS - ","meeting_details":"Contact in Advance for Wheelcahir Accessibility"},{"id":7,"name":"SRO Building Community Room","address":"109 West 129th Street, Basement, (Betw Lenox Avenue &amp; Adam Clayton Powell Blvd) NY 10027","meeting_name":"K.I.S.S. - Keep It Simple (Kiss)","meeting_details":"All meetings are non-smoking."},{"id":8,"name":"Our Lady of Lourdes","address":"469 West 142nd Street, Basement, (Betw Convent &amp; Amsterdam Avenues) NY 10031","meeting_name":"LEARNING TO LIVE SOBER - Learning To Live Sober","meeting_details":""},{"id":9,"name":"","address":"2044 Seventh Avenue, NY 10027","meeting_name":"LIVING CLEAN AND SOBER ON 121st STREET - Living Clean And Sober On 121st Street","meeting_details":"S 2nd, BB 3rd, OD 4th, Living Sober 5th wk."},{"id":10,"name":"S.A.G.E.","address":"127 West 127th Street, (Betw. 7th and Lenox) NY 10027","meeting_name":"MEDITATION COMES TO HARLEM - Meditation Comes To Harlem","meeting_details":"Meeting is closed on holidays"},{"id":11,"name":"Grace Congregational Baptist Church","address":"310 West 139th Street, Basement, (Betw Eighth &amp; Edgecombe Avenues) NY 10037","meeting_name":"MID-HARLEM - Mid-Harlem","meeting_details":"T 1st Monday at 7PM Open 1st Friday 8:10pm, Pitch other Fridays 8:10pm"},{"id":12,"name":"St. James Church","address":"409 West 141st Street, Basement, (@ St. Nicholas Avenue) NY 10031","meeting_name":"MONDAY NIGHT CHALLENGE - Monday Night Challenge","meeting_details":""},{"id":13,"name":"Riverside Church","address":"91 Claremont Avenue, 4th Floor, Room 414, (Betw. Broadway &amp; Riverside Drive)) NY 10027","meeting_name":"PRIMARY PURPOSE - Primary Purpose","meeting_details":""},{"id":14,"name":"Upper Manhattan Mental Health Center","address":"1727 Amsterdam Avenue, 1st Floor in the rear., (@ 145th Street) NY 10031","meeting_name":"PROMISES TWO FOR ONE - Promises Two For One","meeting_details":"1st Sun-OD; 2nd Sun-S; 3rd Sun-Topic; 4th Sun-T; 5th Sun-OD"},{"id":15,"name":"Our Lady of Lourdes Church","address":"469 West 142nd Street, Basement, (Betw Convent &amp; Amsterdam Avenues) NY 10037","meeting_name":"REALITY CHECK - Reality Check","meeting_details":"S 4th Saturday Men's Meeting"},{"id":16,"name":"Riverside Church","address":"91 Claremont Avenue, @ The Cloisters Club Room, (1 Block West of Broadway &amp; 1/2 Block North of 120th Street) NY 10027","meeting_name":"RIVERSIDE - Riverside","meeting_details":"Non-Smoking Meeting."},{"id":17,"name":"St. Aloysius School","address":"219 West 132nd Street, Cafeteria, (Betw. Adam Clayton Powell Blvd. &amp; F. Douglass Blvd.) NY 10027","meeting_name":"RIVERTON - Riverton","meeting_details":"S 2nd & T 4th Tue All meetings are non-smoking. No children allowed at meetings."},{"id":18,"name":"Salem United Methodist Church Community Center","address":"211 West 129th Street, Downstairs in the Gym, (@ Adam Clayton Powell Blvd.) NY 10027","meeting_name":"SALEM - Salem","meeting_details":"O 2nd Wednesday"},{"id":19,"name":"Convent Baptist Church Education Building","address":"425 West 144th Street, 1st Floor, (Betw. Convent Avenue &amp; Hamilton Terrace) NY 10031","meeting_name":"SOBER ADULT MEN - Sober Adult Men","meeting_details":"Men's Meeting"},{"id":20,"name":"St. Phillip's Church","address":"204 West 134th Street, Basement, (Betw Adam C. Powell &amp; Frederick Douglas Blvds) NY 10030","meeting_name":"ST. NICHOLAS - St. Nicholas","meeting_details":"S 2nd, C 3rd, BB 4th, & Grapevine 5th Thu."},{"id":21,"name":"Harlem Hospital King Pavilion","address":"506 Lenox Avenue, Room #3101, 3rd Floor, (@ 135 Street) NY 10037","meeting_name":"STEPS 3 and 11 - Steps Three-Eleven","meeting_details":"B 1st, OD 2nd, S3 3rd, C Literature 4th, & S11 5th Sun."},{"id":22,"name":"Council Center for Problems of Living","address":"1727 Amsterdam Avenue, 1st floor in the rear, @ 145th St. 10031","meeting_name":"SUGAR HILL - ","meeting_details":""},{"id":23,"name":"","address":"1854 Amsterdam Avenue, Basment, (Corner of 152nd Street) NY 10031","meeting_name":"TUESDAY BIG BOOK STUDY - Tuesday Big Book Study","meeting_details":""},{"id":24,"name":"Our Lady of Lourdes Church","address":"469 West 142nd Street, Basement, (Betw. Convent &amp; Amsterdam Avenues 10031","meeting_name":"UPTOWN BIG BOOK WORKSHOP - ","meeting_details":"Meeting meets each Saturday from mid-August thru mid-December"},{"id":25,"name":"Metropolitan AME Church","address":"58-66 West 135th Street, (Betw Malcolm X Boulevard &amp; 5th Avenue) NY 10037","meeting_name":"YOU MAY CARE AFTER - You May Care After","meeting_details":"Non-Smoking Meeting."}],"events":[{"location_id":0,"events":{"event_times":[{"event_number":0,"event_id":0,"eventDay":"Wednesdays","startTime":"6:00 PM","endTime":"7:00 PM"},{"event_number":1,"event_id":1,"eventDay":"Mondays","startTime":"7:00 PM","endTime":"8:00 PM"}],"event_types":[{"event_number":0,"event_id":0,"event_type":"BB = Big Book meeting"},{"event_number":1,"event_id":1,"event_type":"B = Beginners meeting"}],"event_special_interests":[]}},{"location_id":1,"events":{"event_times":[{"event_number":0,"event_id":100,"eventDay":"Wednesdays","startTime":"10:00 AM","endTime":"11:00 AM"},{"event_number":1,"event_id":101,"eventDay":"Thursdays","startTime":"10:00 AM","endTime":"11:00 AM"},{"event_number":2,"event_id":102,"eventDay":"Fridays","startTime":"10:00 AM","endTime":"11:00 AM"},{"event_number":3,"event_id":103,"eventDay":"Tuesdays","startTime":"10:00 AM","endTime":"11:00 AM"}],"event_types":[{"event_number":0,"event_id":100,"event_type":"B = Beginners meeting"},{"event_number":1,"event_id":101,"event_type":"BB = Big Book meeting"},{"event_number":2,"event_id":102,"event_type":"S = Step meeting"},{"event_number":3,"event_id":103,"event_type":"OD = Open Discussion meeting"}],"event_special_interests":[]}},{"location_id":2,"events":{"event_times":[{"event_number":0,"event_id":200,"eventDay":"Saturdays","startTime":"7:30 AM","endTime":"8:30 AM"}],"event_types":[{"event_number":0,"event_id":200,"event_type":"OD = Open Discussion meeting"}],"event_special_interests":[]}},{"location_id":3,"events":{"event_times":[{"event_number":0,"event_id":300,"eventDay":"Saturdays","startTime":"11:30 AM","endTime":"1:00 PM"}],"event_types":[{"event_number":0,"event_id":300,"event_type":"OD = Open Discussion meeting"}],"event_special_interests":[]}},{"location_id":4,"events":{"event_times":[{"event_number":0,"event_id":400,"eventDay":"Mondays","startTime":"12:15 PM","endTime":"1:15 PM"},{"event_number":1,"event_id":401,"eventDay":"Wednesdays","startTime":"12:15 PM","endTime":"1:15 PM"},{"event_number":2,"event_id":402,"eventDay":"Fridays","startTime":"12:15 PM","endTime":"1:15 PM"}],"event_types":[{"event_number":0,"event_id":400,"event_type":"B = Beginners meeting"},{"event_number":1,"event_id":401,"event_type":"S = Step meeting"},{"event_number":2,"event_id":402,"event_type":"OD = Open Discussion meeting"}],"event_special_interests":[]}},{"location_id":5,"events":{"event_times":[{"event_number":0,"event_id":500,"eventDay":"Thursdays","startTime":"8:00 PM","endTime":"9:00 PM"}],"event_types":[{"event_number":0,"event_id":500,"event_type":"B = Beginners meeting"}],"event_special_interests":[]}},{"location_id":6,"events":{"event_times":[{"event_number":0,"event_id":600,"eventDay":"Mondays","startTime":"12:00 PM","endTime":"1:00 PM"}],"event_types":[{"event_number":0,"event_id":600,"event_type":"O = Open meeting"}],"event_special_interests":[{"event_number":0,"event_id":600,"special_interest":"Agnostic"}]}},{"location_id":7,"events":{"event_times":[{"event_number":0,"event_id":700,"eventDay":"Sundays","startTime":"5:30 PM","endTime":"6:30 PM"},{"event_number":1,"event_id":701,"eventDay":"Sundays","startTime":"7:00 PM","endTime":"8:00 PM"}],"event_types":[{"event_number":0,"event_id":700,"event_type":"S = Step meeting"},{"event_number":1,"event_id":701,"event_type":"B = Beginners meeting"}],"event_special_interests":[]}},{"location_id":8,"events":{"event_times":[{"event_number":0,"event_id":800,"eventDay":"Thursdays","startTime":"6:00 PM","endTime":"7:00 PM"}],"event_types":[{"event_number":0,"event_id":800,"event_type":"BB = Big Book meeting"}],"event_special_interests":[]}},{"location_id":9,"events":{"event_times":[{"event_number":0,"event_id":900,"eventDay":"Sundays","startTime":"6:00 PM","endTime":"7:30 PM"}],"event_types":[{"event_number":0,"event_id":900,"event_type":"B = Beginners meeting"}],"event_special_interests":[]}},{"location_id":10,"events":{"event_times":[{"event_number":0,"event_id":1000,"eventDay":"Mondays","startTime":"4:30 PM","endTime":"5:30 PM"}],"event_types":[{"event_number":0,"event_id":1000,"event_type":"C = Closed Discussion meeting"}],"event_special_interests":[]}},{"location_id":11,"events":{"event_times":[{"event_number":0,"event_id":1100,"eventDay":"Mondays","startTime":"7:00 PM","endTime":"8:00 PM"},{"event_number":1,"event_id":1101,"eventDay":"Fridays","startTime":"7:00 PM","endTime":"8:00 PM"},{"event_number":2,"event_id":1102,"eventDay":"Fridays","startTime":"8:00 PM","endTime":"9:00 PM"}],"event_types":[{"event_number":0,"event_id":1100,"event_type":"S = Step meeting"},{"event_number":1,"event_id":1101,"event_type":"B = Beginners meeting"},{"event_number":2,"event_id":1102,"event_type":"O = Open meeting"}],"event_special_interests":[]}},{"location_id":12,"events":{"event_times":[{"event_number":0,"event_id":1200,"eventDay":"Mondays","startTime":"7:00 PM","endTime":"8:00 PM"}],"event_types":[{"event_number":0,"event_id":1200,"event_type":"B = Beginners meeting"}],"event_special_interests":[]}},{"location_id":13,"events":{"event_times":[{"event_number":0,"event_id":1300,"eventDay":"Sundays","startTime":"3:00 PM","endTime":"4:00 PM"}],"event_types":[{"event_number":0,"event_id":1300,"event_type":"OD = Open Discussion meeting"}],"event_special_interests":[]}},{"location_id":14,"events":{"event_times":[{"event_number":0,"event_id":1400,"eventDay":"Sundays","startTime":"9:30 AM","endTime":"10:30 AM"},{"event_number":1,"event_id":1401,"eventDay":"Sundays","startTime":"11:00 AM","endTime":"12:00 PM"}],"event_types":[{"event_number":0,"event_id":1400,"event_type":"B = Beginners meeting"},{"event_number":1,"event_id":1401,"event_type":"C = Closed Discussion meeting"}],"event_special_interests":[]}},{"location_id":15,"events":{"event_times":[{"event_number":0,"event_id":1500,"eventDay":"Saturdays","startTime":"5:00 PM","endTime":"6:00 PM"}],"event_types":[{"event_number":0,"event_id":1500,"event_type":"OD = Open Discussion meeting"}],"event_special_interests":[{"event_number":0,"event_id":1500,"special_interest":"Men"}]}},{"location_id":16,"events":{"event_times":[{"event_number":0,"event_id":1600,"eventDay":"Mondays","startTime":"7:00 PM","endTime":"8:00 PM"}],"event_types":[{"event_number":0,"event_id":1600,"event_type":"C = Closed Discussion meeting"}],"event_special_interests":[]}},{"location_id":17,"events":{"event_times":[{"event_number":0,"event_id":1700,"eventDay":"Saturdays","startTime":"3:00 PM","endTime":"4:00 PM"},{"event_number":1,"event_id":1701,"eventDay":"Saturdays","startTime":"6:00 PM","endTime":"7:00 PM"},{"event_number":2,"event_id":1702,"eventDay":"Tuesdays","startTime":"8:00 PM","endTime":"9:00 PM"}],"event_types":[{"event_number":0,"event_id":1700,"event_type":"B = Beginners meeting"},{"event_number":1,"event_id":1701,"event_type":"O = Open meeting"}],"event_special_interests":[]}},{"location_id":18,"events":{"event_times":[{"event_number":0,"event_id":1800,"eventDay":"Wednesdays","startTime":"7:30 PM","endTime":"8:30 PM"}],"event_types":[{"event_number":0,"event_id":1800,"event_type":"C = Closed Discussion meeting"}],"event_special_interests":[]}},{"location_id":19,"events":{"event_times":[{"event_number":0,"event_id":1900,"eventDay":"Wednesdays","startTime":"7:00 PM","endTime":"8:00 PM"}],"event_types":[{"event_number":0,"event_id":1900,"event_type":"C = Closed Discussion meeting"}],"event_special_interests":[{"event_number":0,"event_id":1900,"special_interest":"Men"}]}},{"location_id":20,"events":{"event_times":[{"event_number":0,"event_id":2000,"eventDay":"Sundays","startTime":"4:00 PM","endTime":"5:00 PM"},{"event_number":1,"event_id":2001,"eventDay":"Thursdays","startTime":"7:00 PM","endTime":"8:00 PM"}],"event_types":[{"event_number":0,"event_id":2000,"event_type":"O = Open meeting"},{"event_number":1,"event_id":2001,"event_type":"B = Beginners meeting"}],"event_special_interests":[]}},{"location_id":21,"events":{"event_times":[{"event_number":0,"event_id":2100,"eventDay":"Sundays","startTime":"2:00 PM","endTime":"3:00 PM"}],"event_types":[{"event_number":0,"event_id":2100,"event_type":"B = Beginners meeting"}],"event_special_interests":[]}},{"location_id":22,"events":{"event_times":[{"event_number":0,"event_id":2200,"eventDay":"Fridays","startTime":"5:30 PM","endTime":"6:30 PM"}],"event_types":[{"event_number":0,"event_id":2200,"event_type":"B = Beginners meeting"}],"event_special_interests":[]}},{"location_id":23,"events":{"event_times":[{"event_number":0,"event_id":2300,"eventDay":"Tuesdays","startTime":"6:00 PM","endTime":"7:00 PM"}],"event_types":[{"event_number":0,"event_id":2300,"event_type":"BB = Big Book meeting"}],"event_special_interests":[]}},{"location_id":24,"events":{"event_times":[{"event_number":0,"event_id":2400,"eventDay":"Saturdays","startTime":"9:30 AM","endTime":"11:00 AM"}],"event_types":[{"event_number":0,"event_id":2400,"event_type":"BB = Big Book meeting"}],"event_special_interests":[{"event_number":0,"event_id":2400,"special_interest":"Big Book Workshop"}]}},{"location_id":25,"events":{"event_times":[{"event_number":0,"event_id":2500,"eventDay":"Tuesdays","startTime":"6:30 PM","endTime":"7:30 PM"}],"event_types":[{"event_number":0,"event_id":2500,"event_type":"S = Step meeting"}],"event_special_interests":[]}}]}